shipyard_coalesce/__init__.py
shipyard_coalesce/cli/__init__.py
shipyard_coalesce/cli/authtest.py
shipyard_coalesce/cli/determine_status.py
shipyard_coalesce/cli/trigger_sync.py
shipyard_coalesce/coalesce.py
shipyard_coalesce/errors/exceptions.py
shipyard_coalesce-0.2.2.dist-info/METADATA
shipyard_coalesce-0.2.2.dist-info/WHEEL
shipyard_coalesce-0.2.2.dist-info/RECORD
