Metadata-Version: 2.1
Name: shipyard-coalesce
Version: 0.2.2
Summary: A local client for connecting and working with Coalesce
Author: wrp801
Author-email: wespoulsen@gmail.com
Requires-Python: >=3.9,<4.0
Classifier: Programming Language :: Python :: 3
Classifier: Programming Language :: Python :: 3.9
Classifier: Programming Language :: Python :: 3.10
Classifier: Programming Language :: Python :: 3.11
Requires-Dist: requests (>=2.31.0,<3.0.0)
Requires-Dist: shipyard-bp-utils (>=1.0.3,<2.0.0)
Requires-Dist: shipyard-templates (==0.6.2)
